[
  {
    "id": "aHR0cHM6Ly90YXNzLnJ1",
    "title": "Синоптик Леус: первый снегопад в Москве стал одним из самых поздних в XXI веке",
    "description": "По словам специалиста центра погоды \"Фобос\", так поздно в век глобального потепления первый снег пошел лишь однажды - 15 ноября 2008 года",
    "fullText": "По словам специалиста центра погоды \"Фобос\", так поздно в век глобального потепления первый снег пошел лишь однажды - 15 ноября 2008 года",
    "image": "https://images.unsplash.com/photo-1461896836934-ffe607ba8211?w=600",
    "source": "ТАСС Спорт",
    "category": "all",
    "url": "https://tass.ru/obschestvo/25636167",
    "time": "2025-11-15T14:45:59.000Z"
  },
  {
    "id": "aHR0cHM6Ly9zaXJlbmEu",
    "title": "Россия или Чили? Решите исход матча – сделайте свой прогноз",
    "description": "С фрибетом 7777 рублей от Лиги Ставок.",
    "fullText": "С фрибетом 7777 рублей от Лиги Ставок.",
    "image": "https://photobooth.cdn.sports.ru/preset/article/7/86/c8d94976643938848130cdf869d26.jpeg",
    "source": "Sports.ru",
    "category": "all",
    "url": "https://sirena.world/r7ng79",
    "time": "2025-11-15T11:30:00.000Z"
  },
  {
    "id": "aHR0cHM6Ly93d3cuc3Bv",
    "title": "Босс «Феррари» заткнул Хэмилтона: в провалах виновны пилоты, а команда «Ф-1» – супер. Он совсем?!",
    "description": "Проверяем Элканна.",
    "fullText": "Проверяем Элканна.",
    "image": "https://photobooth.cdn.sports.ru/preset/message/0/ea/3d2a6fa06435e939d6a56dd7c55c1.jpeg",
    "source": "Sports.ru",
    "category": "all",
    "url": "https://www.sports.ru/automoto/blogs/3363571.html",
    "time": "2025-11-15T11:10:00.000Z"
  },
  {
    "id": "aHR0cHM6Ly9kdGYucnUv",
    "title": "Состоялся цифровой релиз «Битвы за битвой» Пола Томаса Андерсона",
    "description": "Леонардо ДиКаприо уже пророчат как минимум номинацию на «Оскар» за роль.",
    "fullText": "Леонардо ДиКаприо уже пророчат как минимум номинацию на «Оскар» за роль.",
    "image": "https://leonardo.osnova.io/fd6fa557-2a87-5e6f-b0e4-f99bae53dc9e/",
    "source": "DTF Киберспорт",
    "category": "cybersport",
    "url": "https://dtf.ru/cinema/4158213-tsifrovoy-reliz-bitvy-za-bitvoy?from=rss",
    "time": "2025-11-14T11:37:32.000Z"
  }
]