[
  {
    "id": "aHR0cHM6Ly90YXNzLnJ1",
    "title": "На северо-западе России ожидаются небольшие осадки и ночные заморозки",
    "description": "В НАО ожидается температура минус 2-7 градусов, на западе округа до плюс 3, на востоке до минус 12 градусов",
    "fullText": "В НАО ожидается температура минус 2-7 градусов, на западе округа до плюс 3, на востоке до минус 12 градусов",
    "image": "https://images.unsplash.com/photo-1461896836934-ffe607ba8211?w=600",
    "source": "ТАСС Спорт",
    "category": "all",
    "url": "https://tass.ru/obschestvo/25548893",
    "time": "2025-11-06T04:01:28.000Z"
  },
  {
    "id": "aHR0cHM6Ly9zaXJlbmEu",
    "title": "На каком стадионе Дмитрий Аленичев выиграл Лигу чемпионов?",
    "description": "Ответят только знатоки.",
    "fullText": "Ответят только знатоки.",
    "image": "https://photobooth.cdn.sports.ru/preset/article/4/f4/3e83eb941434f99387a29829f82a6.jpeg",
    "source": "Sports.ru",
    "category": "all",
    "url": "https://sirena.world/z69vfk",
    "time": "2025-11-05T21:30:00.000Z"
  },
  {
    "id": "aHR0cHM6Ly93d3cuc3Bv",
    "title": "«Спартак» – в топ-3 Первой лиги. Тренер раскрыл секреты дерзкого новичка",
    "description": "Как Кострома приближается к РПЛ.",
    "fullText": "Как Кострома приближается к РПЛ.",
    "image": "https://photobooth.cdn.sports.ru/preset/message/1/8b/3b4be1e57410ba062dff462ecbfc0.jpeg",
    "source": "Sports.ru",
    "category": "all",
    "url": "https://www.sports.ru/football/blogs/3362251.html",
    "time": "2025-11-05T21:00:00.000Z"
  },
  {
    "id": "aHR0cHM6Ly9kdGYucnUv",
    "title": "Состоялся анонс игры «Киберслав: Затмение» по мотивам анимационного сериала",
    "description": "Её планируют выпустить в 2027 году.",
    "fullText": "Её планируют выпустить в 2027 году.",
    "image": "https://leonardo.osnova.io/f11f5e0b-05ba-57fd-a634-64f856292a06/",
    "source": "DTF Киберспорт",
    "category": "cybersport",
    "url": "https://dtf.ru/games/4134533-anons-igry-kiberslav-zatmenie?from=rss",
    "time": "2025-11-05T09:56:24.000Z"
  }
]