[
  {
    "id": "aHR0cHM6Ly90YXNzLnJ1",
    "title": "Армения и Азербайджан провели осмотр железнодорожного участка Ерасх - Садарак",
    "description": "",
    "fullText": "",
    "image": "https://images.unsplash.com/photo-1461896836934-ffe607ba8211?w=600",
    "source": "ТАСС Спорт",
    "category": "all",
    "url": "https://tass.ru/ekonomika/26159069",
    "time": "2026-01-15T13:24:52.000Z"
  },
  {
    "id": "aHR0cHM6Ly9zaXJlbmEu",
    "title": "Как Смолов отблагодарил ассистента в матче с «Реалом»?",
    "description": "Яркий момент в карьере Федора.",
    "fullText": "Яркий момент в карьере Федора.",
    "image": "https://photobooth.cdn.sports.ru/preset/article/5/81/310179a38402587afeea619e54ad9.png",
    "source": "Sports.ru",
    "category": "all",
    "url": "https://sirena.world/eftnht",
    "time": "2026-01-15T09:30:00.000Z"
  },
  {
    "id": "aHR0cHM6Ly93d3cuc3Bv",
    "title": "Концовки «Нетс» уже немыслимы без трехочковых от Дёмина",
    "description": "«Бруклин» подвели подборы.",
    "fullText": "«Бруклин» подвели подборы.",
    "image": "https://photobooth.cdn.sports.ru/preset/message/c/91/562ddc97747579c70c76114cb5c41.jpeg",
    "source": "Sports.ru",
    "category": "all",
    "url": "https://www.sports.ru/basketball/blogs/3377065.html",
    "time": "2026-01-15T08:35:00.000Z"
  },
  {
    "id": "aHR0cHM6Ly9kdGYucnUv",
    "title": "Роль Кратоса в сериале God of War получил Райан Херст",
    "description": "Актёр известен по ролям в «Сынах анархии» и «Покинутых».",
    "fullText": "Актёр известен по ролям в «Сынах анархии» и «Покинутых».",
    "image": "https://leonardo.osnova.io/9c825cb7-0a57-5a36-90e5-f24cc630a599/",
    "source": "DTF Киберспорт",
    "category": "cybersport",
    "url": "https://dtf.ru/cinema/4722703-rajan-hyurst-krol-kratos-v-god-of-war?from=rss",
    "time": "2026-01-14T20:19:11.000Z"
  }
]