[
  {
    "id": "aHR0cHM6Ly90YXNzLnJ1",
    "title": "Белоусов поздравил бойцов ВС РФ, освободивших Рог в ДНР",
    "description": "Министр обороны России поблагодарил командование и личный состав за успешное выполнение боевых задач и верность воинскому долгу",
    "fullText": "Министр обороны России поблагодарил командование и личный состав за успешное выполнение боевых задач и верность воинскому долгу",
    "image": "https://cdn-media.tass.ru/fit/400x300_b2b00b17/tass/m2/uploads/i/20250731/8373777.jpg",
    "source": "ТАСС Спорт",
    "category": "all",
    "url": "https://tass.ru/armiya-i-opk/25626207",
    "time": "2025-11-14T10:08:33.000Z"
  },
  {
    "id": "aHR0cHM6Ly9zaXJlbmEu",
    "title": "Кто выиграет итоговый турнир ATP? Выбирайте фаворитов ближайших встреч в Основе",
    "description": "Смотрите трансляции матчей и выигрывайте призы.",
    "fullText": "Смотрите трансляции матчей и выигрывайте призы.",
    "image": "https://photobooth.cdn.sports.ru/preset/article/4/5c/74296ed8d4b9d94952b4a3051a43d.jpeg",
    "source": "Sports.ru",
    "category": "all",
    "url": "https://sirena.world/kmw55s",
    "time": "2025-11-14T07:00:00.000Z"
  },
  {
    "id": "aHR0cHM6Ly93d3cuc3Bv",
    "title": "Норрис теперь точно чемпион «Ф-1»? Вот все сценарии шансов Ферстаппена и Пиастри",
    "description": "Возможна драма с полным равенством очков в финале.",
    "fullText": "Возможна драма с полным равенством очков в финале.",
    "image": "https://photobooth.cdn.sports.ru/preset/message/d/2a/f71b2140a46dc949f6249f2bad54d.jpeg",
    "source": "Sports.ru",
    "category": "all",
    "url": "https://www.sports.ru/betting/blogs/3363546.html",
    "time": "2025-11-14T06:00:00.000Z"
  },
  {
    "id": "aHR0cHM6Ly9kdGYucnUv",
    "title": "Некоторые игроки сообщили, что им удалось оплатить покупки в зарубежных регионах PS Store картами из стран СНГ",
    "description": "Но это может быть баг, да и для региона РФ ничего не изменилось.",
    "fullText": "Но это может быть баг, да и для региона РФ ничего не изменилось.",
    "image": "https://leonardo.osnova.io/222f01d0-4df0-5939-8769-3777b6531c5f/",
    "source": "DTF Киберспорт",
    "category": "cybersport",
    "url": "https://dtf.ru/gameindustry/4152198-oplata-pokupok-v-ps-store-kartami-iz-sng?from=rss",
    "time": "2025-11-13T16:18:32.000Z"
  }
]