[
  {
    "id": "aHR0cHM6Ly90YXNzLnJ1",
    "title": "В Запорожской области более 6,7 тыс. человек остаются без света после атаки ВСУ",
    "description": "Губернатор региона Евгений Балицкий сообщил, что работа по восстановлению электричества продолжается",
    "fullText": "Губернатор региона Евгений Балицкий сообщил, что работа по восстановлению электричества продолжается",
    "image": "https://images.unsplash.com/photo-1461896836934-ffe607ba8211?w=600",
    "source": "ТАСС Спорт",
    "category": "all",
    "url": "https://tass.ru/proisshestviya/26032915",
    "time": "2025-12-27T12:23:49.000Z"
  },
  {
    "id": "aHR0cHM6Ly9zaXJlbmEu",
    "title": "Лишь два аргентинца забили больше 25 голов за «Барсу» в этом веке. Вспомните не Месси?",
    "description": "Придется подумать.",
    "fullText": "Придется подумать.",
    "image": "https://photobooth.cdn.sports.ru/preset/article/e/ed/c81424428406d921c1a24b3be62db.png",
    "source": "Sports.ru",
    "category": "all",
    "url": "https://sirena.world/r58w11",
    "time": "2025-12-27T09:30:00.000Z"
  },
  {
    "id": "aHR0cHM6Ly93d3cuc3Bv",
    "title": "Раздаем награды за треть сезона НБА: Йокич – MVP, Холмгрен – «Замок», лучший тренер – у «Бостона»",
    "description": "Спорить о вкусах – это удовольствие.",
    "fullText": "Спорить о вкусах – это удовольствие.",
    "image": "https://photobooth.cdn.sports.ru/preset/message/e/7d/d7540e0a84ae89f49f8324ac7a35a.jpeg",
    "source": "Sports.ru",
    "category": "all",
    "url": "https://www.sports.ru/basketball/blogs/3372872.html",
    "time": "2025-12-27T09:00:00.000Z"
  },
  {
    "id": "aHR0cHM6Ly9kdGYucnUv",
    "title": "Джек Блэк оценил змей из видеоигр — от Солида Снейка до Йормунганда",
    "description": "Ему полюбились имена некоторых из них.",
    "fullText": "Ему полюбились имена некоторых из них.",
    "image": "https://leonardo.osnova.io/8a8c3e47-fe4c-5981-982a-93ab0a86646e/",
    "source": "DTF Киберспорт",
    "category": "cybersport",
    "url": "https://dtf.ru/games/4558784-dzhek-blek-o-zmeyakh-iz-videoigr?from=rss",
    "time": "2025-12-26T10:13:49.000Z"
  }
]