[
  {
    "id": "aHR0cHM6Ly90YXNzLnJ1",
    "title": "В ГАИ рассказали, когда можно проводить освидетельствование без понятых",
    "description": "Понятых можно не привлекать, если идет видеозапись",
    "fullText": "Понятых можно не привлекать, если идет видеозапись",
    "image": "https://images.unsplash.com/photo-1461896836934-ffe607ba8211?w=600",
    "source": "ТАСС Спорт",
    "category": "all",
    "url": "https://tass.ru/obschestvo/25521183",
    "time": "2025-11-02T02:03:03.000Z"
  },
  {
    "id": "aHR0cHM6Ly9zaXJlbmEu",
    "title": "Сколько шайб забросил Овечкин до попадания на обложку NHL 2K10? Экскурсия по карьере",
    "description": "Великая погоня!",
    "fullText": "Великая погоня!",
    "image": "https://photobooth.cdn.sports.ru/preset/article/3/2d/0447204b045d098189235dd48b8e2.png",
    "source": "Sports.ru",
    "category": "all",
    "url": "https://sirena.world/iha53v",
    "time": "2025-11-01T21:55:00.000Z"
  },
  {
    "id": "aHR0cHM6Ly93d3cuc3Bv",
    "title": "Мирра в костюме, Соболенко в красном, Паолини в платье за €6000 – теннисистки на последнем турнире сезона",
    "description": "Рассматриваем.",
    "fullText": "Рассматриваем.",
    "image": "https://photobooth.cdn.sports.ru/preset/message/7/c5/dd72bff4b4115a5786cf0a5261987.jpeg",
    "source": "Sports.ru",
    "category": "all",
    "url": "https://www.sports.ru/tennis/blogs/3361208.html",
    "time": "2025-11-01T20:15:00.000Z"
  },
  {
    "id": "aHR0cHM6Ly9kdGYucnUv",
    "title": "Nintendo выиграла суд против стримера, который транслировал ещё не вышедшие игры компании — он заплатит 17,5 тысяч долларов",
    "description": "Сам он не сильно пытался защищаться.",
    "fullText": "Сам он не сильно пытался защищаться.",
    "image": "https://leonardo.osnova.io/fd9b2471-dbaf-51f0-856a-302f573bf79c/",
    "source": "DTF Киберспорт",
    "category": "cybersport",
    "url": "https://dtf.ru/gameindustry/4123762-nintendo-vyigrala-sud-protiv-streamera?from=rss",
    "time": "2025-10-31T10:13:00.000Z"
  }
]