[
  {
    "id": "aHR0cHM6Ly90YXNzLnJ1",
    "title": "Семья Шатунова оценивает общий ущерб по делу продюсера Разина в 1 млрд рублей",
    "description": "Ущерб ранее оценили в 500 млн рублей",
    "fullText": "Ущерб ранее оценили в 500 млн рублей",
    "image": "https://cdn-media.tass.ru/fit/400x300_b2b00b17/tass/m2/uploads/i/20260128/8771685.jpg",
    "source": "ТАСС Спорт",
    "category": "all",
    "url": "https://tass.ru/obschestvo/26266731",
    "time": "2026-01-27T22:11:44.000Z"
  },
  {
    "id": "aHR0cHM6Ly9zaXJlbmEu",
    "title": "Угадаете по детскому фото обладателя Кубка Гагарина? А рекордсмена КХЛ?",
    "description": "Сложный тест на знание звезд!",
    "fullText": "Сложный тест на знание звезд!",
    "image": "https://photobooth.cdn.sports.ru/preset/message/3/9a/ac7d85de74ad3a8ee91be7b1daaef.png",
    "source": "Sports.ru",
    "category": "all",
    "url": "https://sirena.world/6jssib",
    "time": "2026-01-27T19:00:00.000Z"
  },
  {
    "id": "aHR0cHM6Ly9kdGYucnUv",
    "title": "Продажи Absolum достигли 500 тысяч копий — в честь этого авторы назвали дату релиза крупного апдейта",
    "description": "Обновление «Нити судьбы» выйдет уже 12 февраля.",
    "fullText": "Обновление «Нити судьбы» выйдет уже 12 февраля.",
    "image": "https://leonardo.osnova.io/97b5e5f7-3662-5636-b411-fa6c238b00e6/",
    "source": "DTF Киберспорт",
    "category": "cybersport",
    "url": "https://dtf.ru/gameindustry/4748437-prodazhi-absolum-previshayut-500-tysyach-kopiy?from=rss",
    "time": "2026-01-27T17:46:32.000Z"
  },
  {
    "id": "aHR0cHM6Ly93d3cuc3Bv",
    "title": "50 км в 50 лет при почти -50°C: приключения Смертина в Оймяконе – как это преодолеть",
    "description": "Уникальные детали.",
    "fullText": "Уникальные детали.",
    "image": "https://photobooth.cdn.sports.ru/preset/message/1/e8/a35f2277049d191035a0a07d965b3.png",
    "source": "Sports.ru",
    "category": "all",
    "url": "https://www.sports.ru/football/blogs/3380219.html",
    "time": "2026-01-27T17:03:00.000Z"
  }
]