[
  {
    "id": "aHR0cHM6Ly90YXNzLnJ1",
    "title": "С экс-главы \"Укрэнерго\" сняли электронный браслет",
    "description": "При этом для Владимира Кудрицкого сохраняются процессуальные ограничения: он должен сдать загранпаспорт, являться по вызову и не общаться со свидетелями по делу",
    "fullText": "При этом для Владимира Кудрицкого сохраняются процессуальные ограничения: он должен сдать загранпаспорт, являться по вызову и не общаться со свидетелями по делу",
    "image": "https://images.unsplash.com/photo-1461896836934-ffe607ba8211?w=600",
    "source": "ТАСС Спорт",
    "category": "all",
    "url": "https://tass.ru/proisshestviya/26278167",
    "time": "2026-01-28T19:51:24.000Z"
  },
  {
    "id": "aHR0cHM6Ly9zaXJlbmEu",
    "title": "1.61 – кэф на победу «ПСЖ» против «Ньюкасла». Ставьте на исход с фрибетом до 15 000 без депозита",
    "description": "Последний день основного этапа ЛЧ.",
    "fullText": "Последний день основного этапа ЛЧ.",
    "image": "https://photobooth.cdn.sports.ru/preset/article/a/9b/09f3660994770a2358d17d79c7a47.jpeg",
    "source": "Sports.ru",
    "category": "all",
    "url": "https://sirena.world/oz8t07",
    "time": "2026-01-28T15:55:00.000Z"
  },
  {
    "id": "aHR0cHM6Ly93d3cuc3Bv",
    "title": "Дембеле зовут в СА, Онана вернется в «Интер»? Главные инсайды дня",
    "description": "Here we go!",
    "fullText": "Here we go!",
    "image": "https://photobooth.cdn.sports.ru/preset/message/1/b9/1f8c195454e02b2ad5e6566f18b5c.jpeg",
    "source": "Sports.ru",
    "category": "all",
    "url": "https://www.sports.ru/football/blogs/3380718.html",
    "time": "2026-01-28T15:30:00.000Z"
  },
  {
    "id": "aHR0cHM6Ly9kdGYucnUv",
    "title": "Мини-сериал по роману «Повелитель мух» выйдет уже 8 февраля — трейлер",
    "description": "Шоу будет состоять из четырёх эпизодов.",
    "fullText": "Шоу будет состоять из четырёх эпизодов.",
    "image": "https://leonardo.osnova.io/d6d75d32-029f-536b-b04d-7c2424461288/-/format/mp4/",
    "source": "DTF Киберспорт",
    "category": "cybersport",
    "url": "https://dtf.ru/cinema/4750169-miniserial-povelitel-mukh?from=rss",
    "time": "2026-01-28T13:32:09.000Z"
  }
]