[
  {
    "id": "aHR0cHM6Ly90YXNzLnJ1",
    "title": "Московское \"Динамо\" взяло реванш у \"Шанхай Дрэгонс\" в КХЛ",
    "description": "Бело-голубые одержали победу в серии буллитов",
    "fullText": "Бело-голубые одержали победу в серии буллитов",
    "image": "https://cdn-media.tass.ru/fit/400x300_b2b00b17/tass/m2/uploads/i/20251016/8531429.jpg",
    "source": "ТАСС Спорт",
    "category": "all",
    "url": "https://tass.ru/sport/25371595",
    "time": "2025-10-16T19:03:39.000Z"
  },
  {
    "id": "aHR0cHM6Ly9zaXJlbmEu",
    "title": "«Авангард» крупно проиграл «Барысу». Что это вообще было?",
    "description": "Показывали на ВидеоСпортсе’’.",
    "fullText": "Показывали на ВидеоСпортсе’’.",
    "image": "https://photobooth.cdn.sports.ru/preset/article/e/19/07f3658b64341a4b69c28e43917ae.jpeg",
    "source": "Sports.ru",
    "category": "all",
    "url": "https://sirena.world/barys-avangard",
    "time": "2025-10-16T16:00:00.000Z"
  },
  {
    "id": "aHR0cHM6Ly93d3cuc3Bv",
    "title": "Джо Маззулла поглумился над журналистами: 57:4 в товарищеском матче тренеров и репортеров",
    "description": "Но всем понравилось.",
    "fullText": "Но всем понравилось.",
    "image": "https://photobooth.cdn.sports.ru/preset/message/a/66/d1754fd424c05b4b84914b2ada148.jpeg",
    "source": "Sports.ru",
    "category": "all",
    "url": "https://www.sports.ru/basketball/blogs/3357523.html",
    "time": "2025-10-16T15:07:00.000Z"
  },
  {
    "id": "aHR0cHM6Ly9kdGYucnUv",
    "title": "Полнометражное аниме по «Человеку-бензопиле» официально покажут в России и Беларуси",
    "description": "С дубляжом от Flarrow Films.",
    "fullText": "С дубляжом от Flarrow Films.",
    "image": "https://leonardo.osnova.io/024d4dba-da6c-530e-9f43-25c77ac9763a/",
    "source": "DTF Киберспорт",
    "category": "cybersport",
    "url": "https://dtf.ru/anime/4091455-chelovek-benzopila-istoriya-reze?from=rss",
    "time": "2025-10-16T10:10:08.000Z"
  }
]