[
  {
    "id": "aHR0cHM6Ly90YXNzLnJ1",
    "title": "На подъезде к Президентскому мосту в Ульяновске произошло массовое ДТП",
    "description": "В аварии пострадал человек",
    "fullText": "В аварии пострадал человек",
    "image": "https://images.unsplash.com/photo-1461896836934-ffe607ba8211?w=600",
    "source": "ТАСС Спорт",
    "category": "all",
    "url": "https://tass.ru/proisshestviya/25374713",
    "time": "2025-10-17T06:33:15.000Z"
  },
  {
    "id": "aHR0cHM6Ly9zaXJlbmEu",
    "title": "FONBET Кубок России вернулся! Проверьте, как вы помните историю турнира",
    "description": "Тест с классными призами.",
    "fullText": "Тест с классными призами.",
    "image": "https://photobooth.cdn.sports.ru/preset/article/e/00/0ebd4f54d47da959694d467cc6146.jpeg",
    "source": "Sports.ru",
    "category": "all",
    "url": "https://sirena.world/v37hq4",
    "time": "2025-10-16T19:00:00.000Z"
  },
  {
    "id": "aHR0cHM6Ly93d3cuc3Bv",
    "title": "Сиднейский марафон ­– новый мейджор. Как попасть? Сколько стоит поездка?",
    "description": "Истории наших финишеров.",
    "fullText": "Истории наших финишеров.",
    "image": "https://photobooth.cdn.sports.ru/preset/message/8/99/2292e9cf54033b9fea98e56cc713b.jpeg",
    "source": "Sports.ru",
    "category": "all",
    "url": "https://www.sports.ru/health/blogs/3354135.html",
    "time": "2025-10-16T17:30:00.000Z"
  },
  {
    "id": "aHR0cHM6Ly9kdGYucnUv",
    "title": "Группа Hollywood Undead отменила концерты в России",
    "description": "Это было быстро.",
    "fullText": "Это было быстро.",
    "image": "https://leonardo.osnova.io/ce9a76a2-fef1-57d3-ae49-b4c884df344c/",
    "source": "DTF Киберспорт",
    "category": "cybersport",
    "url": "https://dtf.ru/music/4091384-hollywood-undead-otmenili-kontserty-v-rossii?from=rss",
    "time": "2025-10-16T09:28:27.000Z"
  }
]