[
  {
    "id": "aHR0cHM6Ly90YXNzLnJ1",
    "title": "В Ливане сообщили об атаке израильского дрона на джип в Набатии",
    "description": "По информации ВС республики, ранены двое военных",
    "fullText": "По информации ВС республики, ранены двое военных",
    "image": "https://images.unsplash.com/photo-1461896836934-ffe607ba8211?w=600",
    "source": "ТАСС Спорт",
    "category": "all",
    "url": "https://tass.ru/mezhdunarodnaya-panorama/27588705",
    "time": "2026-05-30T22:07:50.000Z"
  },
  {
    "id": "aHR0cHM6Ly9tLnNwb3J0",
    "title": "30 лучших игроков Лондона и Парижа – узнаете всех?",
    "description": "В Невидимке.",
    "fullText": "В Невидимке.",
    "image": "https://photobooth.cdn.sports.ru/preset/article/f/08/68bbe52f24992b67ad6e9750b817e.png",
    "source": "Sports.ru",
    "category": "all",
    "url": "https://m.sports.ru/invisible/?utm_source=native",
    "time": "2026-05-30T21:30:00.000Z"
  },
  {
    "id": "aHR0cHM6Ly93d3cuc3Bv",
    "title": "Как «ПСЖ» прогнал эгоистов и построил династию",
    "description": "Рассказывает Любовь Курчавова.",
    "fullText": "Рассказывает Любовь Курчавова.",
    "image": "https://photobooth.cdn.sports.ru/preset/message/3/18/de77d69bf4c1aba85179f5d2c826a.jpeg",
    "source": "Sports.ru",
    "category": "all",
    "url": "https://www.sports.ru/football/blogs/3409209.html",
    "time": "2026-05-30T19:50:00.000Z"
  },
  {
    "id": "aHR0cHM6Ly9kdGYucnUv",
    "title": "Хоррор «Закулисье реальности» установил рекорд фильмов студии A24 по сборам на предварительных показах в США",
    "description": "Судя по всему, картина обойдёт «Падение империи» по результату за первый уикенд.",
    "fullText": "Судя по всему, картина обойдёт «Падение империи» по результату за первый уикенд.",
    "image": "https://leonardo.osnova.io/2442e76b-cd35-50fc-bbc3-4862c4e0b009/",
    "source": "DTF Киберспорт",
    "category": "cybersport",
    "url": "https://dtf.ru/cinema/5090543-horor-zakulise-realnosti-rekord-a24?from=rss",
    "time": "2026-05-29T17:31:10.000Z"
  }
]