[
  {
    "id": "aHR0cHM6Ly9zaXJlbmEu",
    "title": "На каком стадионе Дмитрий Аленичев выиграл Лигу чемпионов?",
    "description": "Ответят только знатоки!",
    "fullText": "Ответят только знатоки!",
    "image": "https://photobooth.cdn.sports.ru/preset/article/4/f4/3e83eb941434f99387a29829f82a6.jpeg",
    "source": "Sports.ru",
    "category": "all",
    "url": "https://sirena.world/z69vfk",
    "time": "2025-10-24T14:00:00.000Z"
  },
  {
    "id": "aHR0cHM6Ly92aWRlby5z",
    "title": "Наши обыграли Северную Македонию. Смотрите матч женской сборной Юрия Красножана",
    "description": "Комментатор: Владимир Заводников.",
    "fullText": "Комментатор: Владимир Заводников.",
    "image": "https://photobooth.cdn.sports.ru/preset/article/e/05/23847d25e4535bf3272ae6a6062c6.jpeg",
    "source": "Sports.ru",
    "category": "all",
    "url": "https://video.sports.ru/stream/zo7pG1y2g2r_k4X0oPPXoYm4dYmJ88xgAMRf_YaV_y8",
    "time": "2025-10-24T12:25:00.000Z"
  },
  {
    "id": "aHR0cHM6Ly93d3cuc3Bv",
    "title": "Интервью с лучшим русским тяжеловесом UFC Александром Волковым – это он читает Сенеку",
    "description": "Идет за поясом.",
    "fullText": "Идет за поясом.",
    "image": "https://photobooth.cdn.sports.ru/preset/message/f/de/7ffc3bb5a4db1a079a3711e2ee4ed.png",
    "source": "Sports.ru",
    "category": "all",
    "url": "https://www.sports.ru/boxing/blogs/3358593.html",
    "time": "2025-10-24T11:25:00.000Z"
  },
  {
    "id": "aHR0cHM6Ly9kdGYucnUv",
    "title": "Создатели командного киберпанк-шутера Defect показали четырёхминутный геймплейный трейлер",
    "description": "Под саундтрек Мика Гордона.",
    "fullText": "Под саундтрек Мика Гордона.",
    "image": "https://leonardo.osnova.io/fa3bf68a-c6a1-5a58-9e7d-29c43812cd1e/-/format/mp4/",
    "source": "DTF Киберспорт",
    "category": "cybersport",
    "url": "https://dtf.ru/games/4107842-geymplejnyj-trejler-defect?from=rss",
    "time": "2025-10-24T06:33:44.000Z"
  },
  {
    "id": "aHR0cHM6Ly90YXNzLnJ1",
    "title": "В МВД заявили, что информация о стрельбе возле ТРЦ \"Щелковский\" не поступала",
    "description": "Предварительно, пострадавших нет",
    "fullText": "Предварительно, пострадавших нет",
    "image": "https://images.unsplash.com/photo-1461896836934-ffe607ba8211?w=600",
    "source": "ТАСС Спорт",
    "category": "all",
    "url": "https://tass.ru/proisshestviya/24133329",
    "time": "2025-06-04T11:02:07.000Z"
  }
]