[
  {
    "id": "aHR0cHM6Ly90YXNzLnJ1",
    "title": "Забравшиеся на Эмпайр-стейт-билдинг россияне предстали перед судом в Нью-Йорке",
    "description": "Иван Биркус и Ангелина Николау не признали вину",
    "fullText": "Иван Биркус и Ангелина Николау не признали вину",
    "image": "https://images.unsplash.com/photo-1461896836934-ffe607ba8211?w=600",
    "source": "ТАСС Спорт",
    "category": "all",
    "url": "https://tass.ru/obschestvo/27880389",
    "time": "2026-07-02T17:38:40.000Z"
  },
  {
    "id": "aHR0cHM6Ly9zaXJlbmEu",
    "title": "Португалия с Роналду vs Хорватия с Модричем. Следим за матчем 1/16 с фрибетом до 15 000!",
    "description": "Кто пройдет дальше?",
    "fullText": "Кто пройдет дальше?",
    "image": "https://photobooth.cdn.sports.ru/preset/article/a/1e/6d593b90a4d1a9f6f7407b31892ad.jpeg",
    "source": "Sports.ru",
    "category": "all",
    "url": "https://sirena.world/materialf",
    "time": "2026-07-02T15:30:00.000Z"
  },
  {
    "id": "aHR0cHM6Ly93d3cuc3Bv",
    "title": "135 млн за Андерсона от «Ман Сити»! В топ-5 по цене за всю историю",
    "description": "Рядом с Исаком и Коутиньо.",
    "fullText": "Рядом с Исаком и Коутиньо.",
    "image": "https://photobooth.cdn.sports.ru/preset/message/b/3f/6b92d25be49b08f694f1b0b637f92.jpeg",
    "source": "Sports.ru",
    "category": "all",
    "url": "https://www.sports.ru/football/blogs/3418085.html",
    "time": "2026-07-02T15:15:00.000Z"
  },
  {
    "id": "aHR0cHM6Ly9zcGVjaWFs",
    "title": "Месси vs Роналду: наша эпоха – все о главной дуэли века. Мультимедийный лонгрид Спортса’’",
    "description": "Двое великих.",
    "fullText": "Двое великих.",
    "image": "https://photobooth.cdn.sports.ru/preset/article/7/96/9a72a1a6748d192190461bf54e0da.jpeg",
    "source": "Sports.ru",
    "category": "all",
    "url": "https://specials.sports.ru/goats/",
    "time": "2026-07-02T15:00:00.000Z"
  },
  {
    "id": "aHR0cHM6Ly9kdGYucnUv",
    "title": "«Идеальна для тех, кто хочет страдать»: Никита Буянов о Fragmentary Order",
    "description": "Разработчики готовят много уникальных механик.",
    "fullText": "Разработчики готовят много уникальных механик.",
    "image": "https://leonardo.osnova.io/f8f48675-86d2-51b0-9de8-5be01fa5767e/",
    "source": "DTF Киберспорт",
    "category": "cybersport",
    "url": "https://dtf.ru/games/5161408-nikita-buyanov-o-fragmentary-order?from=rss",
    "time": "2026-07-02T10:11:28.000Z"
  }
]