[
  {
    "id": "aHR0cHM6Ly90YXNzLnJ1",
    "title": "Экс-советник Саркози считает Макрона худшим президентом Франции",
    "description": "По словам Алена Минка, французский президент ошибочно \"считает себя самым умным и хитрым, чтобы решать любые проблемы\"",
    "fullText": "По словам Алена Минка, французский президент ошибочно \"считает себя самым умным и хитрым, чтобы решать любые проблемы\"",
    "image": "https://images.unsplash.com/photo-1461896836934-ffe607ba8211?w=600",
    "source": "ТАСС Спорт",
    "category": "all",
    "url": "https://tass.ru/mezhdunarodnaya-panorama/25549551",
    "time": "2025-11-06T06:04:46.000Z"
  },
  {
    "id": "aHR0cHM6Ly9zaXJlbmEu",
    "title": "Кого мы закрасили на этой фотографии?",
    "description": "Вопрос из квиза про ЛЧ.",
    "fullText": "Вопрос из квиза про ЛЧ.",
    "image": "https://photobooth.cdn.sports.ru/preset/article/d/94/e1ad42fc24ef389630708b0cd24c9.jpeg",
    "source": "Sports.ru",
    "category": "all",
    "url": "https://sirena.world/z69vfk",
    "time": "2025-11-06T04:30:00.000Z"
  },
  {
    "id": "aHR0cHM6Ly93d3cuc3Bv",
    "title": "«Поздно пить боржоми, Женя». Рылов вдруг захотел нейтральный статус",
    "description": "А что случилось?",
    "fullText": "А что случилось?",
    "image": "https://photobooth.cdn.sports.ru/preset/message/9/ac/7811276a442919f915d75797358ac.jpeg",
    "source": "Sports.ru",
    "category": "all",
    "url": "https://www.sports.ru/aquatics/blogs/3362220.html",
    "time": "2025-11-05T22:10:00.000Z"
  },
  {
    "id": "aHR0cHM6Ly9kdGYucnUv",
    "title": "Режиссёр «Игры в имитацию» снимет биографический фильм об Ibelin — игроке в World of Warcraft, который страдал мышечной дистрофией",
    "description": "У ленты появился актёрский состав — в него вошли Стивен Грэм, Изабела Мерсед, Энтони Хопкинс и другие артисты.",
    "fullText": "У ленты появился актёрский состав — в него вошли Стивен Грэм, Изабела Мерсед, Энтони Хопкинс и другие артисты.",
    "image": "https://leonardo.osnova.io/87fd89b6-477e-53d3-a67a-f1cfb642c94f/",
    "source": "DTF Киберспорт",
    "category": "cybersport",
    "url": "https://dtf.ru/cinema/4135011-biograficheskiy-film-ob-ibelin-geymer-ez-world-of-warcraft?from=rss",
    "time": "2025-11-05T14:20:02.000Z"
  }
]