[
  {
    "id": "aHR0cHM6Ly90YXNzLnJ1",
    "title": "ВЦИОМ: уровень доверия россиян Путину превышает 80%",
    "description": "Деятельность правительства РФ одобряют 46,3% опрошенных, свидетельствуют данные аналитического центра",
    "fullText": "Деятельность правительства РФ одобряют 46,3% опрошенных, свидетельствуют данные аналитического центра",
    "image": "https://cdn-media.tass.ru/fit/400x300_b2b00b17/tass/m2/uploads/i/20250128/8033165.jpg",
    "source": "ТАСС Спорт",
    "category": "all",
    "url": "https://tass.ru/obschestvo/25893831",
    "time": "2025-12-12T08:11:54.000Z"
  },
  {
    "id": "aHR0cHM6Ly9zaXJlbmEu",
    "title": "40 идей новогодних подарков для фанатов спорта в новом тесте",
    "description": "Наш подарок всем неопределившимся!",
    "fullText": "Наш подарок всем неопределившимся!",
    "image": "https://photobooth.cdn.sports.ru/preset/article/8/5c/306bbe2ea471d8d74552e58724578.png",
    "source": "Sports.ru",
    "category": "all",
    "url": "https://sirena.world/znslnq",
    "time": "2025-12-12T04:30:00.000Z"
  },
  {
    "id": "aHR0cHM6Ly9kdGYucnUv",
    "title": "Frictional Games представила Ontos — «духовную наследницу» Soma",
    "description": "Одну из главных ролей в триллере исполнил Стеллан Скарсгард.",
    "fullText": "Одну из главных ролей в триллере исполнил Стеллан Скарсгард.",
    "image": "https://leonardo.osnova.io/67463a2e-8cc1-5252-899e-18a99c9de4fe/",
    "source": "DTF Киберспорт",
    "category": "cybersport",
    "url": "https://dtf.ru/games/4526941-frictional-games-anosirovala-ontos-naslednitsu-soma?from=rss",
    "time": "2025-12-12T01:45:33.000Z"
  },
  {
    "id": "aHR0cHM6Ly93d3cuc3Bv",
    "title": "Березуцкому в «Урале» поможет экс-главный тренер 2Drots – ради этого ушел из клуба",
    "description": "2D рассматривают легенду «Локо».",
    "fullText": "2D рассматривают легенду «Локо».",
    "image": "https://photobooth.cdn.sports.ru/preset/message/b/5f/e302428fa4f70a338ba14e07d2188.jpeg",
    "source": "Sports.ru",
    "category": "all",
    "url": "https://www.sports.ru/mediafootball/blogs/3370067.html",
    "time": "2025-12-11T22:00:00.000Z"
  }
]