[
  {
    "id": "aHR0cHM6Ly90YXNzLnJ1",
    "title": "FT: ни одна страна еще не подтвердила участия в стабилизационных силах в Газе",
    "description": "По данным газеты, ни одно государство также не проявило инициативы по разоружению радикального палестинского движения ХАМАС силовым путем",
    "fullText": "По данным газеты, ни одно государство также не проявило инициативы по разоружению радикального палестинского движения ХАМАС силовым путем",
    "image": "https://images.unsplash.com/photo-1461896836934-ffe607ba8211?w=600",
    "source": "ТАСС Спорт",
    "category": "all",
    "url": "https://tass.ru/mezhdunarodnaya-panorama/26043655",
    "time": "2025-12-29T08:42:21.000Z"
  },
  {
    "id": "aHR0cHM6Ly9tLnNwb3J0",
    "title": "Спортс’’ выпустил свой журнал",
    "description": "Вы уже можете его заказать.",
    "fullText": "Вы уже можете его заказать.",
    "image": "https://photobooth.cdn.sports.ru/preset/message/2/7a/cf1a2a6e7446ba902d7ac5323a6c1.png",
    "source": "Sports.ru",
    "category": "all",
    "url": "https://m.sports.ru/yearbook/?ref=pechatnoe&ref2=editorial&ref3=matherial_direct#/payment",
    "time": "2025-12-29T07:00:00.000Z"
  },
  {
    "id": "aHR0cHM6Ly9zNW8ucnUv",
    "title": "Вся карьера Овечкина – гонка. Проедьте ее с ним!",
    "description": "Он не останавливается.",
    "fullText": "Он не останавливается.",
    "image": "https://photobooth.cdn.sports.ru/preset/article/0/81/9807c4d6243c9beadf8555135857b.png",
    "source": "Sports.ru",
    "category": "all",
    "url": "https://s5o.ru/special/supertop-iframe/",
    "time": "2025-12-29T07:00:00.000Z"
  },
  {
    "id": "aHR0cHM6Ly93d3cuc3Bv",
    "title": "Соболенко проиграла Кириосу в «Битве полов» – что это вообще было?",
    "description": "Разбор.",
    "fullText": "Разбор.",
    "image": "https://photobooth.cdn.sports.ru/preset/message/0/f1/666e7f34c4ff88139cffc249e87f6.jpeg",
    "source": "Sports.ru",
    "category": "all",
    "url": "https://www.sports.ru/tennis/blogs/3373576.html",
    "time": "2025-12-28T23:00:00.000Z"
  },
  {
    "id": "aHR0cHM6Ly9kdGYucnUv",
    "title": "Утечка: ассеты BioShock 4 и подробности об игре",
    "description": "Действие, по всей видимости, развернётся в заледенелой местности.",
    "fullText": "Действие, по всей видимости, развернётся в заледенелой местности.",
    "image": "https://leonardo.osnova.io/ea215e4b-4ecc-5a31-a9b9-e1d95847cafe/",
    "source": "DTF Киберспорт",
    "category": "cybersport",
    "url": "https://dtf.ru/games/4568055-bioshock-4-podrobnosti-i-utechka-assetov?from=rss",
    "time": "2025-12-28T10:48:38.000Z"
  }
]