[
  {
    "id": "aHR0cHM6Ly90YXNzLnJ1",
    "title": "Кабмин подготовил второй пакет мер защиты граждан от кибермошенников",
    "description": "Планируется ввести запрет на международные входящие звонки без согласия абонента, уточнил вице-премьер - руководитель аппарата правительства Дмитрий Григоренко",
    "fullText": "Планируется ввести запрет на международные входящие звонки без согласия абонента, уточнил вице-премьер - руководитель аппарата правительства Дмитрий Григоренко",
    "image": "https://images.unsplash.com/photo-1461896836934-ffe607ba8211?w=600",
    "source": "ТАСС Спорт",
    "category": "all",
    "url": "https://tass.ru/obschestvo/25862961",
    "time": "2025-12-09T17:16:05.000Z"
  },
  {
    "id": "aHR0cHM6Ly9zaXJlbmEu",
    "title": "2.02 – на «Интер», 3.75 – на «Ливерпуль». Выбирайте фаворита с фрибетом 2000!",
    "description": "Бонус от Bettery.",
    "fullText": "Бонус от Bettery.",
    "image": "https://photobooth.cdn.sports.ru/preset/article/d/5d/f1910cd004484b38ee98d1ed20e9c.png",
    "source": "Sports.ru",
    "category": "all",
    "url": "https://sirena.world/aabsdw",
    "time": "2025-12-09T13:30:00.000Z"
  },
  {
    "id": "aHR0cHM6Ly93d3cuc3Bv",
    "title": "Как «Айнтрахт» захватил «Камп Ноу» – исторический позор «Барсы»",
    "description": "«Они захватили наш стадион!»",
    "fullText": "«Они захватили наш стадион!»",
    "image": "https://photobooth.cdn.sports.ru/preset/message/d/b5/030e7be83426bb13801b609f96cd9.jpeg",
    "source": "Sports.ru",
    "category": "all",
    "url": "https://www.sports.ru/football/blogs/3369324.html",
    "time": "2025-12-09T13:05:00.000Z"
  },
  {
    "id": "aHR0cHM6Ly9kdGYucnUv",
    "title": "Анонсирована VR-игра The Boys: Trigger Warning по мотивам «Пацанов»",
    "description": "Выход состоится в 2026 году.",
    "fullText": "Выход состоится в 2026 году.",
    "image": "https://leonardo.osnova.io/bcf2391e-cf6f-58e7-8c2d-7ee0828bcfb0/-/format/mp4/",
    "source": "DTF Киберспорт",
    "category": "cybersport",
    "url": "https://dtf.ru/games/4521239-anons-vr-igry-the-boys-trigger-warning?from=rss",
    "time": "2025-12-09T12:59:38.000Z"
  }
]