[
  {
    "id": "aHR0cHM6Ly9zaXJlbmEu",
    "title": "Тест про языки и футбол: выпускникам МГИМО будет легче",
    "description": "Справятся и те, кто учил немецкий в школе.",
    "fullText": "Справятся и те, кто учил немецкий в школе.",
    "image": "https://photobooth.cdn.sports.ru/preset/article/c/be/6463365bd4322842b903112b98ee5.png",
    "source": "Sports.ru",
    "category": "all",
    "url": "https://sirena.world/eftnht",
    "time": "2026-01-06T14:00:00.000Z"
  },
  {
    "id": "aHR0cHM6Ly93d3cuc3Bv",
    "title": "Он играет в теннис с ахиллом мертвого донора в груди",
    "description": "Коккинакис творит историю.",
    "fullText": "Коккинакис творит историю.",
    "image": "https://photobooth.cdn.sports.ru/preset/message/4/1e/484242dd94e8788aa930eb513cee1.jpeg",
    "source": "Sports.ru",
    "category": "all",
    "url": "https://www.sports.ru/tennis/blogs/3375151.html",
    "time": "2026-01-06T11:48:00.000Z"
  },
  {
    "id": "aHR0cHM6Ly9kdGYucnUv",
    "title": "LG анонсировала «беспроводной» OLED-телевизор с толщиной корпуса 9 мм",
    "description": "Цену пока не раскрыли.",
    "fullText": "Цену пока не раскрыли.",
    "image": "https://leonardo.osnova.io/45d28beb-0697-5d66-8579-cd9955c506a5/",
    "source": "DTF Киберспорт",
    "category": "cybersport",
    "url": "https://dtf.ru/hard/4682723-lg-besprovodnoj-oled-televizor-9-mm?from=rss",
    "time": "2026-01-05T12:36:54.000Z"
  },
  {
    "id": "aHR0cHM6Ly90YXNzLnJ1",
    "title": "В МВД заявили, что информация о стрельбе возле ТРЦ \"Щелковский\" не поступала",
    "description": "Предварительно, пострадавших нет",
    "fullText": "Предварительно, пострадавших нет",
    "image": "https://images.unsplash.com/photo-1461896836934-ffe607ba8211?w=600",
    "source": "ТАСС Спорт",
    "category": "all",
    "url": "https://tass.ru/proisshestviya/24133329",
    "time": "2025-06-04T11:02:07.000Z"
  }
]