[
  {
    "id": "aHR0cHM6Ly9zaXJlbmEu",
    "title": "Кто из игроков НХЛ едет на Олимпиаду?",
    "description": "Тест на знание звезд сборных.",
    "fullText": "Тест на знание звезд сборных.",
    "image": "https://photobooth.cdn.sports.ru/preset/article/d/b1/89174675840fea3bf6c1b0d2a1946.png",
    "source": "Sports.ru",
    "category": "all",
    "url": "https://sirena.world/iedj8h",
    "time": "2026-02-09T07:00:00.000Z"
  },
  {
    "id": "aHR0cHM6Ly93d3cuc3Bv",
    "title": "«‎У меня было все: слава, деньги, футбол, а внутри – пустой». Денис Черышев, каким вы его не знали",
    "description": "Интервью Спортсу’‘.",
    "fullText": "Интервью Спортсу’‘.",
    "image": "https://photobooth.cdn.sports.ru/preset/message/1/96/1953c84d34cc7b11536715bc50674.png",
    "source": "Sports.ru",
    "category": "all",
    "url": "https://www.sports.ru/football/blogs/3382890.html",
    "time": "2026-02-09T06:37:00.000Z"
  },
  {
    "id": "aHR0cHM6Ly9kdGYucnUv",
    "title": "Глава Embark о дальнейшей поддержке ARC Raiders: «Мы разрабатываем на ходу, поэтому пока поделились только общими планами»",
    "description": "Игроки будут получать подробности ближе к обновлениям.",
    "fullText": "Игроки будут получать подробности ближе к обновлениям.",
    "image": "https://leonardo.osnova.io/c9272fd2-c3d6-504f-b333-eb367586600d/",
    "source": "DTF Киберспорт",
    "category": "cybersport",
    "url": "https://dtf.ru/games/4770902-podderzhka-arc-raiders-ot-embark-plany-i-kommentarii-glavy-studii?from=rss",
    "time": "2026-02-08T12:41:18.000Z"
  },
  {
    "id": "aHR0cHM6Ly90YXNzLnJ1",
    "title": "В МВД заявили, что информация о стрельбе возле ТРЦ \"Щелковский\" не поступала",
    "description": "Предварительно, пострадавших нет",
    "fullText": "Предварительно, пострадавших нет",
    "image": "https://images.unsplash.com/photo-1461896836934-ffe607ba8211?w=600",
    "source": "ТАСС Спорт",
    "category": "all",
    "url": "https://tass.ru/proisshestviya/24133329",
    "time": "2025-06-04T11:02:07.000Z"
  }
]