[
  {
    "id": "aHR0cHM6Ly90YXNzLnJ1",
    "title": "Рынок акций РФ рос более чем на 2,5%",
    "description": "Индекс Мосбиржи превышал 2 200 пункта",
    "fullText": "Индекс Мосбиржи превышал 2 200 пункта",
    "image": "https://images.unsplash.com/photo-1461896836934-ffe607ba8211?w=600",
    "source": "ТАСС Спорт",
    "category": "all",
    "url": "https://tass.ru/ekonomika/27912363",
    "time": "2026-07-13T12:09:49.000Z"
  },
  {
    "id": "aHR0cHM6Ly9tLnNwb3J0",
    "title": "Вспомните 30 легенд ЧМ всех времен?",
    "description": "Иньеста, Зидан, Месси…",
    "fullText": "Иньеста, Зидан, Месси…",
    "image": "https://photobooth.cdn.sports.ru/preset/article/b/da/c8623bc47411dbc2eed2cdc8c83e0.png",
    "source": "Sports.ru",
    "category": "all",
    "url": "https://m.sports.ru/invisible/?utm_source=native",
    "time": "2026-07-13T09:30:00.000Z"
  },
  {
    "id": "aHR0cHM6Ly93d3cuc3Bv",
    "title": "Кружева, кожаные куртки, коврики для ванной – как бренды спасались от скуки на «Уимблдоне»?",
    "description": "Модный обзор.",
    "fullText": "Модный обзор.",
    "image": "https://photobooth.cdn.sports.ru/preset/message/7/06/90c1a4b2149149ebff94719201320.jpeg",
    "source": "Sports.ru",
    "category": "all",
    "url": "https://www.sports.ru/tennis/blogs/3419988.html",
    "time": "2026-07-13T07:40:00.000Z"
  },
  {
    "id": "aHR0cHM6Ly9kdGYucnUv",
    "title": "Аликс Вилтон Риган закончила основной процесс записи озвучки Лары Крофт в Legacy of Atlantis",
    "description": "Работа заняла у неё четыре года.",
    "fullText": "Работа заняла у неё четыре года.",
    "image": "https://leonardo.osnova.io/343215b1-17b4-5248-8d09-41f6e182ac82/",
    "source": "DTF Киберспорт",
    "category": "cybersport",
    "url": "https://dtf.ru/games/5180349-aliks-vilton-rigan-zavershila-ozvuchku-lary-kroft?from=rss",
    "time": "2026-07-12T14:49:44.000Z"
  }
]