[
  {
    "id": "aHR0cHM6Ly90YXNzLnJ1",
    "title": "В Приангарье запустили производство конвейерных цепей полного цикла",
    "description": "После выхода на проектную мощность планируется выпускать ежегодно до 15 тыс. м продукции под брендом \"Стальное звено\"",
    "fullText": "После выхода на проектную мощность планируется выпускать ежегодно до 15 тыс. м продукции под брендом \"Стальное звено\"",
    "image": "https://images.unsplash.com/photo-1461896836934-ffe607ba8211?w=600",
    "source": "ТАСС Спорт",
    "category": "all",
    "url": "https://tass.ru/ekonomika/25993555",
    "time": "2025-12-23T05:22:03.000Z"
  },
  {
    "id": "aHR0cHM6Ly9jeWJlci5z",
    "title": "26 главных фильмов 2026 года",
    "description": "Заносим в календарь.",
    "fullText": "Заносим в календарь.",
    "image": "https://photobooth.cdn.sports.ru/preset/article/8/9b/868b8d9234f838d1115b353a352b3.jpeg",
    "source": "Sports.ru",
    "category": "all",
    "url": "https://cyber.sports.ru/cinema/blogs/3369412.html",
    "time": "2025-12-22T21:10:00.000Z"
  },
  {
    "id": "aHR0cHM6Ly93d3cuc3Bv",
    "title": "Символическая сборная «Зенита» за 25 лет. Халк, Аршавин и Кержаков в атаке",
    "description": "Выбор Дорского.",
    "fullText": "Выбор Дорского.",
    "image": "https://photobooth.cdn.sports.ru/preset/message/9/de/fa00c23e445f889750147d1e22756.jpeg",
    "source": "Sports.ru",
    "category": "all",
    "url": "https://www.sports.ru/football/blogs/3371768.html",
    "time": "2025-12-22T19:35:00.000Z"
  },
  {
    "id": "aHR0cHM6Ly9zaXJlbmEu",
    "title": "🥕 Кто из футбольных звезд будет рад мешку моркови на Новый год?",
    "description": "Выбираем подарки.",
    "fullText": "Выбираем подарки.",
    "image": "https://photobooth.cdn.sports.ru/preset/article/c/2c/52277cf054c069221120a4d602ef4.png",
    "source": "Sports.ru",
    "category": "all",
    "url": "https://sirena.world/83v9je",
    "time": "2025-12-22T19:30:00.000Z"
  },
  {
    "id": "aHR0cHM6Ly9kdGYucnUv",
    "title": "Аниме «Гачиакута» продлили на второй сезон",
    "description": "Также по тайтлу выпустят экшен-RPG с элементами «выживача».",
    "fullText": "Также по тайтлу выпустят экшен-RPG с элементами «выживача».",
    "image": "https://leonardo.osnova.io/aa28a693-33d9-51c4-ae21-526cab5a64b8/",
    "source": "DTF Киберспорт",
    "category": "cybersport",
    "url": "https://dtf.ru/anime/4550438-anime-gachiakuta-vtoroy-sezon-i-anons-igry?from=rss",
    "time": "2025-12-22T14:28:49.000Z"
  }
]