[
  {
    "id": "aHR0cHM6Ly90YXNzLnJ1",
    "title": "Захарова: Каллас успела \"протухнуть\", рассуждая о геополитическом значении рыбы",
    "description": "Глава дипломатии ЕС ранее заявила, что рыба \"имеет геополитическое значение\" в проекте 21-го пакета санкций против России",
    "fullText": "Глава дипломатии ЕС ранее заявила, что рыба \"имеет геополитическое значение\" в проекте 21-го пакета санкций против России",
    "image": "https://cdn-media.tass.ru/fit/400x300_b2b00b17/tass/m2/uploads/i/20250123/8022737.jpg",
    "source": "ТАСС Спорт",
    "category": "all",
    "url": "https://tass.ru/politika/27916877",
    "time": "2026-07-14T15:36:58.000Z"
  },
  {
    "id": "aHR0cHM6Ly9zaXJlbmEu",
    "title": "Кто выйдет в финал ЧМ – Франция или Испания? Ставьте на фаворита в Лиге Ставок",
    "description": "С фрибетом 4х2000 новым игрокам.",
    "fullText": "С фрибетом 4х2000 новым игрокам.",
    "image": "https://photobooth.cdn.sports.ru/preset/article/e/7b/01718fe4f4cb3be463d2b03fd2642.jpeg",
    "source": "Sports.ru",
    "category": "all",
    "url": "https://sirena.world/Q30EYSE",
    "time": "2026-07-14T15:30:00.000Z"
  },
  {
    "id": "aHR0cHM6Ly92aWRlby5z",
    "title": "Мегаподкаст Хабиба и Смолова: поговорили про UFC, ЧМ-2026 и разборки с Роналдо",
    "description": "Подкаст с Непобежденным.",
    "fullText": "Подкаст с Непобежденным.",
    "image": "https://photobooth.cdn.sports.ru/preset/article/f/aa/c2900d28a4b61a73b64e48c91b175.jpeg",
    "source": "Sports.ru",
    "category": "all",
    "url": "https://video.sports.ru/video/waNBnf1BB4CN5cA5RSWncSq_3NWrFOTr4CPm9aSJTjE",
    "time": "2026-07-14T15:20:00.000Z"
  },
  {
    "id": "aHR0cHM6Ly9nb28uc3Uv",
    "title": "Олисе в 1 ассисте от рекорда Пеле – догонит уже с Испанией? Можно взять за 3.2",
    "description": "С фрибетом до 1500 рублей.",
    "fullText": "С фрибетом до 1500 рублей.",
    "image": "https://photobooth.cdn.sports.ru/preset/article/7/84/7587ed40448e2b4b46cd39f2b95a3.jpeg",
    "source": "Sports.ru",
    "category": "all",
    "url": "https://goo.su/LEZzd",
    "time": "2026-07-14T13:30:00.000Z"
  },
  {
    "id": "aHR0cHM6Ly93d3cuc3Bv",
    "title": "Родри снова играет как лучший полузащитник мира",
    "description": "Испания еще больше команда Родри.",
    "fullText": "Испания еще больше команда Родри.",
    "image": "https://photobooth.cdn.sports.ru/preset/message/7/1e/4dcdfb7cd401a8d6bb4faa746f073.jpeg",
    "source": "Sports.ru",
    "category": "all",
    "url": "https://www.sports.ru/football/blogs/3420988.html",
    "time": "2026-07-14T11:50:00.000Z"
  },
  {
    "id": "aHR0cHM6Ly9kdGYucnUv",
    "title": "Интернет-криптид «Мультяшный кот» получит полнометражный фильм",
    "description": "Это уже вторая лента на основе персонажей Тревора Хендерсона.",
    "fullText": "Это уже вторая лента на основе персонажей Тревора Хендерсона.",
    "image": "https://leonardo.osnova.io/09c1cbeb-5fc2-5d0c-945b-ff80c333b0c4/",
    "source": "DTF Киберспорт",
    "category": "cybersport",
    "url": "https://dtf.ru/cinema/5183662-multyashnyy-kot-polnometrazhnyy-film?from=rss",
    "time": "2026-07-14T09:45:50.000Z"
  }
]