[
  {
    "id": "aHR0cHM6Ly90YXNzLnJ1",
    "title": "Минимальный бюджет клубов РФ по бенди составляет от 100 до 150 млн рублей",
    "description": "Директор ФХМР Сергей Мяус отметил, что без участия властей вопрос финансирования клубов пока не решить",
    "fullText": "Директор ФХМР Сергей Мяус отметил, что без участия властей вопрос финансирования клубов пока не решить",
    "image": "https://images.unsplash.com/photo-1461896836934-ffe607ba8211?w=600",
    "source": "ТАСС Спорт",
    "category": "all",
    "url": "https://tass.ru/sport/25587867",
    "time": "2025-11-11T08:09:14.000Z"
  },
  {
    "id": "aHR0cHM6Ly93d3cuc3Bv",
    "title": "СКА испортил «Авангарду» праздник. Омск столкнулся с вратарем-стеной",
    "description": "Иванов сделал 43 сэйва.",
    "fullText": "Иванов сделал 43 сэйва.",
    "image": "https://photobooth.cdn.sports.ru/preset/message/e/1d/c2f68b53f4e86bda7b825d4cf2967.jpeg",
    "source": "Sports.ru",
    "category": "all",
    "url": "https://www.sports.ru/hockey/blogs/3363376.html",
    "time": "2025-11-11T01:00:00.000Z"
  },
  {
    "id": "aHR0cHM6Ly9zaXJlbmEu",
    "title": "Этого испанца из «Юнайтед» вспомнили только 40% игроков! Сможете?",
    "description": "Проверьте себя.",
    "fullText": "Проверьте себя.",
    "image": "https://photobooth.cdn.sports.ru/preset/article/d/24/084b127fd4f808b6c848753daf8bb.png",
    "source": "Sports.ru",
    "category": "all",
    "url": "https://sirena.world/pweyv2",
    "time": "2025-11-11T00:30:00.000Z"
  },
  {
    "id": "aHR0cHM6Ly9kdGYucnUv",
    "title": "Для Battlefield 6 разрабатывают как минимум девять игровых режимов",
    "description": "Не факт, что все доберутся до релиза.",
    "fullText": "Не факт, что все доберутся до релиза.",
    "image": "https://leonardo.osnova.io/64940a2b-6cf9-56d3-a06a-fcf44b02f069/",
    "source": "DTF Киберспорт",
    "category": "cybersport",
    "url": "https://dtf.ru/games/4145015-battlefield-6-devyat-novykh-igrovykh-rezhimov?from=rss",
    "time": "2025-11-10T13:59:07.000Z"
  }
]