[
  {
    "id": "aHR0cHM6Ly90YXNzLnJ1",
    "title": "\"Газпром-медиа\": Россия и Сербия имеют потенциал для совместного производства кино",
    "description": "Холдинг рассмотрит возможность съемок программы \"Выжить в Сербии\", продолжающей серию, в рамках которой уже вышли выпуски об ОАЭ, Турции и Узбекистане",
    "fullText": "Холдинг рассмотрит возможность съемок программы \"Выжить в Сербии\", продолжающей серию, в рамках которой уже вышли выпуски об ОАЭ, Турции и Узбекистане",
    "image": "https://images.unsplash.com/photo-1461896836934-ffe607ba8211?w=600",
    "source": "ТАСС Спорт",
    "category": "all",
    "url": "https://tass.ru/ekonomika/27200413",
    "time": "2026-04-23T13:13:06.000Z"
  },
  {
    "id": "aHR0cHM6Ly9zaXJlbmEu",
    "title": "«Спартак» vs «Краснодар»: ставьте с фрибетом и побеждайте",
    "description": "Бонус до 20 000 рублей от Балтбет.",
    "fullText": "Бонус до 20 000 рублей от Балтбет.",
    "image": "https://photobooth.cdn.sports.ru/preset/article/f/bd/3095e986347e1ab1bec9a0879eb59.jpeg",
    "source": "Sports.ru",
    "category": "all",
    "url": "https://sirena.world/ax9xnz",
    "time": "2026-04-23T09:30:00.000Z"
  },
  {
    "id": "aHR0cHM6Ly93d3cuc3Bv",
    "title": "«Я бы признался, если бы задел». Дивеев и Семак не понимают, откуда пенальти",
    "description": "А вы?",
    "fullText": "А вы?",
    "image": "https://photobooth.cdn.sports.ru/preset/message/e/8f/b6909c1f849f88d62e648659a4049.jpeg",
    "source": "Sports.ru",
    "category": "all",
    "url": "https://www.sports.ru/football/blogs/3399746.html",
    "time": "2026-04-23T09:15:00.000Z"
  },
  {
    "id": "aHR0cHM6Ly9kdGYucnUv",
    "title": "Марика, Поедатель отбросов и главный герой: фото и видео со съёмок киноадаптации Elden Ring",
    "description": "Алекс Гарленд вовсю работает над фильмом.",
    "fullText": "Алекс Гарленд вовсю работает над фильмом.",
    "image": "https://leonardo.osnova.io/6ff7b5c7-fdb3-57fe-822b-b6b4d1f6a763/",
    "source": "DTF Киберспорт",
    "category": "cybersport",
    "url": "https://dtf.ru/cinema/5013698-ekranizatsiya-elden-ring-marika-poedatel-otbrosov?from=rss",
    "time": "2026-04-22T18:07:23.000Z"
  }
]